copula_sim/__init__.py
copula_sim/gaussian_coplas.py
copulasim-0.1.0.dist-info/METADATA
copulasim-0.1.0.dist-info/WHEEL
copulasim-0.1.0.dist-info/top_level.txt
copulasim-0.1.0.dist-info/RECORD
