Metadata-Version: 2.1
Name: copulasim
Version: 0.1.0
Summary: A simple Python package for working with Gaussian Copulas
Home-page: https://github.com/yourusername/my_package
Author: Ben Melcher
Author-email: blmelcher@outlook.com
License: MIT
Requires-Python: >=3.6
